petstore_test_sdk/__init__.py
petstore_test_sdk/sdk.py
petstore_test_sdk/hooks/__init__.py
petstore_test_sdk/hooks/hook.py
petstore_test_sdk/models/__init__.py
petstore_test_sdk/models/base.py
petstore_test_sdk/models/pet.py
petstore_test_sdk/models/utils/cast_models.py
petstore_test_sdk/models/utils/json_map.py
petstore_test_sdk/net/__init__.py
petstore_test_sdk/net/environment/__init__.py
petstore_test_sdk/net/environment/environment.py
petstore_test_sdk/net/headers/__init__.py
petstore_test_sdk/net/headers/base_header.py
petstore_test_sdk/net/request_chain/__init__.py
petstore_test_sdk/net/request_chain/request_chain.py
petstore_test_sdk/net/request_chain/handlers/__init__.py
petstore_test_sdk/net/request_chain/handlers/base_handler.py
petstore_test_sdk/net/request_chain/handlers/hook_handler.py
petstore_test_sdk/net/request_chain/handlers/http_handler.py
petstore_test_sdk/net/request_chain/handlers/retry_handler.py
petstore_test_sdk/net/transport/__init__.py
petstore_test_sdk/net/transport/request.py
petstore_test_sdk/net/transport/request_error.py
petstore_test_sdk/net/transport/response.py
petstore_test_sdk/net/transport/serializer.py
petstore_test_sdk/net/transport/utils.py
petstore_test_sdk/services/__init__.py
petstore_test_sdk/services/pets.py
petstore_test_sdk/services/utils/base_service.py
petstore_test_sdk/services/utils/default_headers.py
petstore_test_sdk/services/utils/validator.py
jimbobbennett_petstore_sdk-1.0.2.dist-info/METADATA
jimbobbennett_petstore_sdk-1.0.2.dist-info/WHEEL
jimbobbennett_petstore_sdk-1.0.2.dist-info/top_level.txt
jimbobbennett_petstore_sdk-1.0.2.dist-info/RECORD
