Metadata-Version: 2.1
Name: jimbobbennett-petstore-sdk
Version: 1.0.2
Requires-Python: >=3.7
Requires-Dist: requests >=2.31.0
